[{"ranges":[],"childrenIndices":[1],"outLinks":[],"outIndex":0,"traceId":"root"},{"ranges":[{"begin":{"line":4,"column":9},"end":{"line":4,"column":18}},{"begin":{"line":5,"column":13},"end":{"line":5,"column":17}}],"childrenIndices":[2],"parentIndex":0,"outLinks":[],"outIndex":0,"traceId":"4"},{"ranges":[{"begin":{"line":8,"column":13},"end":{"line":8,"column":22}}],"childrenIndices":[3],"parentIndex":1,"outLinks":[],"outIndex":0,"traceId":"6"},{"ranges":[{"begin":{"line":4,"column":9},"end":{"line":4,"column":18}},{"begin":{"line":5,"column":13},"end":{"line":5,"column":17}}],"childrenIndices":[],"parentIndex":2,"link":{"begin":{"line":8,"column":17},"end":{"line":8,"column":19}},"outLinks":[{"begin":{"line":3,"column":24},"end":{"line":3,"column":26}}],"outIndex":2,"traceId":"0"}]